{"homeAlias":"/","nodes":{"/test/test/":{"id":0,"title":"Test","url":"/test/test/","group":"none","home":false,"outBound":[],"neighbors":["/"],"backLinks":["/"],"noteIcon":"","hide":false,"size":0},"/Без названия 2/":{"id":1,"title":"Без названия 2","url":"/Без названия 2/","group":"ttt","home":false,"outBound":["hgjgjh","Входящие","Баннер - драконьи кости.jpg","../_/attachments/баннеры/Баннер - драконьи кости.jpg"],"neighbors":["/"],"backLinks":["/"],"noteIcon":"","hide":false,"size":0},"/Без названия 1/":{"id":2,"title":"Без названия 1","url":"/Без названия 1/","group":"gggg","home":false,"outBound":[],"neighbors":["/"],"backLinks":["/"],"noteIcon":"","hide":false,"size":0},"/Без названия 3/":{"id":3,"title":"Без названия 3","url":"/Без названия 3/","group":"none","home":false,"outBound":[],"neighbors":["/"],"backLinks":["/"],"noteIcon":"","hide":false,"size":0},"/":{"id":4,"title":"Без названия","url":"/","group":"none","home":true,"outBound":["/test/test/","/","/Без названия 1/","/Без названия 2/","/Без названия 3/","/zametki/legenda-znachki/"],"neighbors":["/test/test/","/","/Без названия 1/","/Без названия 2/","/Без названия 3/","/zametki/legenda-znachki/"],"backLinks":["/"],"noteIcon":"","hide":false,"size":6},"/zametki/legenda-znachki/":{"id":5,"title":"Легенда (значки)","url":"/zametki/legenda-znachki/","group":"none","home":false,"outBound":[],"neighbors":["/"],"backLinks":["/"],"noteIcon":"","hide":false,"size":0}},"links":[{"source":4,"target":0},{"source":4,"target":4},{"source":4,"target":2},{"source":4,"target":1},{"source":4,"target":3},{"source":4,"target":5}]}